help50lite/__init__.py
help50lite/__main__.py
help50lite/cli.py
help50lite/engine.py
help50lite/registry.py
help50lite/helpers/__init__.py
help50lite/helpers/make_helpers.py
help50lite-0.1.0.dist-info/METADATA
help50lite-0.1.0.dist-info/WHEEL
help50lite-0.1.0.dist-info/entry_points.txt
help50lite-0.1.0.dist-info/top_level.txt
help50lite-0.1.0.dist-info/RECORD
