Metadata-Version: 2.4
Name: help50lite
Version: 0.1.0
Summary: A lightweight version of help50 with multilingual support.
Author-email: Ramon Rodrigues <ramon@ramonrodrigues.dev>
License: MIT
Requires-Python: >=3.8
